ws_bulk_report_generator/__init__.py
ws_bulk_report_generator/_version.py
ws_bulk_report_generator/bulk_report_generator.py
ws_bulk_report_generator-24.1.1.dist-info/LICENSE
ws_bulk_report_generator-24.1.1.dist-info/METADATA
ws_bulk_report_generator-24.1.1.dist-info/WHEEL
ws_bulk_report_generator-24.1.1.dist-info/entry_points.txt
ws_bulk_report_generator-24.1.1.dist-info/top_level.txt
ws_bulk_report_generator-24.1.1.dist-info/RECORD
