Metadata-Version: 2.1
Name: ws-bulk-report-generator
Version: 24.1.1
Summary: WS Bulk Report Generator
Home-page: https://github.com/whitesource-ps/ws-bulk-report-generator
Author: WhiteSource Professional Services
Author-email: ps@whitesourcesoftware.com
License: LICENSE.txt
Platform: UNKNOWN
Classifier: Programming Language :: Python :: 3.8
Classifier: Programming Language :: Python :: 3.9
Classifier: License :: OSI Approved :: Apache Software License
Classifier: Operating System :: OS Independent
Requires-Python: >=3.7
License-File: LICENSE
Requires-Dist: ws-sdk ==23.12.2
Requires-Dist: DateTime ==4.9
Requires-Dist: requests ==2.31.0
Requires-Dist: XlsxWriter ==3.0.3
